[
  {
    "id": 67148392,
    "ticketUniqueKey": "2148173328@64000032@38",
    "status": "open",
    "inQuestion": null,
    "inTransition": null,
    "origin": "Ativo",
    "waitTime": null,
    "attendanceTime": null,
    "closedAt": null,
    "inChatBot": null,
    "chatBotPath": null,
    "unreadMessages": 0,
    "lastMessage": null,
    "lastMessageType": null,
    "enableAutoFinish": true,
    "autoFinishDate": null,
    "lastMessageDate": "2000-01-01T02:00:00.000Z",
    "lastMessageDateNotFromMe": null,
    "windowExpirationTimestamp": null,
    "isGroup": false,
    "inAvaliation": null,
    "avaliated": null,
    "avaliationTime": null,
    "messageRetry": null,
    "writingMessage": null,
    "lastMessageUserId": null,
    "markedAsUnread": false,
    "absenceMessageDisabled": null,
    "isFixed": null,
    "isTransfered": null,
    "userId": 4400030,
    "contactId": 2148173328,
    "whatsappId": 64000032,
    "whatsappApiId": null,
    "metaId": null,
    "queueId": 64000070,
    "companyId": 38,
    "createdAt": "2026-04-17T13:42:18.000Z",
    "updatedAt": "2026-04-17T13:42:18.000Z",
    "contact": {
      "id": 2148173328,
      "name": "PURO NATUREBA - ARIANNY - MA",
      "number": "559985012525",
      "contactUniqueKey": "559985012525@38",
      "email": "",
      "profilePicUrl": "https://d2mytgzbagllkr.cloudfront.net/production/38/38-2148173328-profilePic?Expires=1893456000&Key-Pair-Id=K1I60S7Y6MHGME&Signature=LWVwy4zlz9aOQ9wdGD3JfXvyIZUIxOZG7AtEiS8vjOL-cWsYzONCpK0qN~rNKs2p4~e8GzzmCkwwefhJjKxptVjKm18zRa6e6-FLsbPHH3V6191PzLeq0fmYwWgjKpg8brieM~wOhZP45KEf4TNrVK82ykMYDpW~-lNjk~BnUVEFHhKT8lvq2~9qIkDbAsC8HrzmcFyWc6EOTw8YrQ4KBKqrUbncSFu2KO2BoIaYCKmGmX-wm7jJznRKSOpETc1xBFbUyNebbhzrEP2RGt6mbtObO3uwwjPzD2SA5vHSOJB9vkCdUoAt6Z1nGkdUluqIagAD6h20eOhcCm7ZGU-x1g__",
      "channel": "whatsapp",
      "isGroup": false,
      "userId": null,
      "queueId": null,
      "companyId": 38,
      "lid": "256801060708382@lid",
      "createdAt": "2025-09-12T20:50:06.000Z",
      "updatedAt": "2026-03-04T17:46:23.000Z"
    },
    "user": {
      "photo": "https://d2mytgzbagllkr.cloudfront.net/production/38/logo%20lp.png?Expires=1893456000&Key-Pair-Id=K1I60S7Y6MHGME&Signature=CnErM5h3iIgCHCXsiFsMxxOfXLCBYWn9O08FoGdgoyRoXkffZZKWUcQ0cHxnWMY8OZQOrN5tVwk0370mzYYEZ6jC9hBZwE3IPBv1jPzvCsIwgRiltPE3XUiqapzsaeTPpT4UFkXwaKw~u8~6jGZDVhO0FQL81FOE0kiUlQQFrM-fXsjm1iF5RUjb15LUi2Ax-bYDs06ebAJyVAp-zGvYI4xVtyKzMVNv7J37CRjwjQ~OI0dQgtiaQYM-SBcd6hvwu~K-HtgOJ57wR8CPKOE1YswJ0We1MvNGGwDk5tBsftxACz3-2rNlzUGOCS0TTh94cpROz7tnSEfoE1P04huETw__",
      "id": 4400030,
      "name": "Larissa",
      "email": "representante.laripadilha@gmail.com",
      "passwordHash": "$2a$08$dSq7KFI/WDtcsWOs4uE8c.AC1klbgBZNXFhUmd8qyLFB9bzoIx3r2",
      "tokenVersion": 0,
      "profile": "admin",
      "whatsappId": null,
      "metaId": null,
      "WhatsappApiId": null,
      "ramal": "#null",
      "companyId": 38,
      "active": true,
      "deleted": false,
      "deviceLowMs": 0,
      "isOnline": false,
      "createdAt": "2023-03-24T16:50:22.000Z",
      "updatedAt": "2026-04-17T20:36:59.000Z"
    },
    "whatsapp": {
      "id": 64000032,
      "name": "Central Vitao 💚",
      "sessionId": null,
      "session": null,
      "qrcode": "",
      "status": "CONNECTED",
      "number": "554135236546",
      "battery": null,
      "plugged": null,
      "retries": 0,
      "greetingMessage": null,
      "farewellMessage": null,
      "isDefault": false,
      "allowCall": false,
      "containerIdPort": "fca4f3ae-6b73-414c-9c44-6c558827e561:whatsapp-microservice",
      "companyId": 38,
      "version": "6.4.11",
      "contactForDisconnectionWarning": "5547997676172",
      "phoneCallMessage": "As chamadas de voz e vídeo estão desabilitadas para esse WhatsApp, por favor enviar uma mensagem de texto ou áudio. Obrigado(a)",
      "createdAt": "2025-04-07T18:06:12.000Z",
      "updatedAt": "2026-04-17T00:04:30.000Z"
    }
  },
  {
    "id": 67147884,
    "ticketUniqueKey": "4400521@4400008@38",
    "status": "open",
    "inQuestion": null,
    "inTransition": null,
    "origin": "Receptivo",
    "waitTime": "2872",
    "attendanceTime": null,
    "closedAt": null,
    "inChatBot": null,
    "chatBotPath": null,
    "unreadMessages": 0,
    "lastMessage": "*Larissa*:\nPerdão Sil, nas próximas vezes acompanho certinho para o estoque estar atualizado e não ocorrer atrasos mais 😓",
    "lastMessageType": "chat",
    "enableAutoFinish": true,
    "autoFinishDate": null,
    "lastMessageDate": "2026-04-17T13:58:17.000Z",
    "lastMessageDateNotFromMe": "2026-04-17T13:50:28.000Z",
    "windowExpirationTimestamp": null,
    "isGroup": false,
    "inAvaliation": null,
    "avaliated": null,
    "avaliationTime": null,
    "messageRetry": null,
    "writingMessage": false,
    "lastMessageUserId": 4400030,
    "markedAsUnread": false,
    "absenceMessageDisabled": null,
    "isFixed": null,
    "isTransfered": false,
    "userId": 4400030,
    "contactId": 4400521,
    "whatsappId": 4400008,
    "whatsappApiId": null,
    "metaId": null,
    "queueId": 4400001,
    "companyId": 38,
    "createdAt": "2026-04-17T12:13:09.000Z",
    "updatedAt": "2026-04-17T13:58:17.000Z",
    "contact": {
      "id": 4400521,
      "name": "DIVINA TERRA - SILVANE - SC",
      "number": "554991042034",
      "contactUniqueKey": "554991042034@38",
      "email": "",
      "profilePicUrl": "https://d2mytgzbagllkr.cloudfront.net/production/38/38-4400521-profilePic?Expires=1893456000&Key-Pair-Id=K1I60S7Y6MHGME&Signature=foOTnLQj9ZUNLS5K11xG24qdye2bFPo7kSknPbPLRP4UJDh6ra~3vHAQwHNKBGC0JAWUR6Dtrq6MwFDY5zMuhDHHdOkGxFQwxm5HjmyO-Gy4~WsXvbaYR3l13L5Q8k7mgyY9iH-E1Zjd6f37ihT~PD7xFrv0OXzD~4W~rwgGUjxWVOPWfKp6PkAt5wsINQmP2LUCv4iBIGVTj86BvVwc171OvIro9u~1hR55E5W~3Z2v9smhfJVfG0xSuZ6D60pUvjhGYPUO87xWLNdZPUqu1aaLssLEUAJz~T2khvi7nXsKMdxmvOb-m1NYfeTeVGLsIEBl7gyW8neHuw2mD24sVw__",
      "channel": "whatsapp",
      "isGroup": false,
      "userId": null,
      "queueId": 4400001,
      "companyId": 38,
      "lid": "251977174929446@lid",
      "createdAt": "2022-08-24T14:56:29.000Z",
      "updatedAt": "2026-01-12T13:01:18.000Z"
    },
    "user": {
      "photo": "https://d2mytgzbagllkr.cloudfront.net/production/38/logo%20lp.png?Expires=1893456000&Key-Pair-Id=K1I60S7Y6MHGME&Signature=CnErM5h3iIgCHCXsiFsMxxOfXLCBYWn9O08FoGdgoyRoXkffZZKWUcQ0cHxnWMY8OZQOrN5tVwk0370mzYYEZ6jC9hBZwE3IPBv1jPzvCsIwgRiltPE3XUiqapzsaeTPpT4UFkXwaKw~u8~6jGZDVhO0FQL81FOE0kiUlQQFrM-fXsjm1iF5RUjb15LUi2Ax-bYDs06ebAJyVAp-zGvYI4xVtyKzMVNv7J37CRjwjQ~OI0dQgtiaQYM-SBcd6hvwu~K-HtgOJ57wR8CPKOE1YswJ0We1MvNGGwDk5tBsftxACz3-2rNlzUGOCS0TTh94cpROz7tnSEfoE1P04huETw__",
      "id": 4400030,
      "name": "Larissa",
      "email": "representante.laripadilha@gmail.com",
      "passwordHash": "$2a$08$dSq7KFI/WDtcsWOs4uE8c.AC1klbgBZNXFhUmd8qyLFB9bzoIx3r2",
      "tokenVersion": 0,
      "profile": "admin",
      "whatsappId": null,
      "metaId": null,
      "WhatsappApiId": null,
      "ramal": "#null",
      "companyId": 38,
      "active": true,
      "deleted": false,
      "deviceLowMs": 0,
      "isOnline": false,
      "createdAt": "2023-03-24T16:50:22.000Z",
      "updatedAt": "2026-04-17T20:36:59.000Z"
    },
    "whatsapp": {
      "id": 4400008,
      "name": "Mais Granel 🧡",
      "sessionId": 7782,
      "session": "",
      "qrcode": "",
      "status": "CONNECTED",
      "number": "554733075968",
      "battery": null,
      "plugged": null,
      "retries": 0,
      "greetingMessage": null,
      "farewellMessage": null,
      "isDefault": true,
      "allowCall": false,
      "containerIdPort": "d30e6122-07f0-466f-9406-7ea4ef7e4afc:11250",
      "companyId": 38,
      "version": "6.4.11",
      "contactForDisconnectionWarning": "5547997676172",
      "phoneCallMessage": "As chamadas de voz e vídeo estão desabilitadas para esse WhatsApp, por favor enviar uma mensagem de texto ou áudio. Obrigado(a)",
      "createdAt": "2023-01-13T17:15:07.000Z",
      "updatedAt": "2026-04-17T00:07:10.000Z"
    }
  },
  {
    "id": 67147525,
    "ticketUniqueKey": "11058859@4400008@38",
    "status": "open",
    "inQuestion": null,
    "inTransition": null,
    "origin": "Receptivo",
    "waitTime": "8926",
    "attendanceTime": null,
    "closedAt": null,
    "inChatBot": null,
    "chatBotPath": null,
    "unreadMessages": 0,
    "lastMessage": "*Larissa*:\nTudo bem? Como posso lhe ajudar?",
    "lastMessageType": "chat",
    "enableAutoFinish": true,
    "autoFinishDate": null,
    "lastMessageDate": "2026-04-17T16:26:49.000Z",
    "lastMessageDateNotFromMe": "2026-04-17T16:04:59.000Z",
    "windowExpirationTimestamp": null,
    "isGroup": false,
    "inAvaliation": null,
    "avaliated": null,
    "avaliationTime": null,
    "messageRetry": null,
    "writingMessage": false,
    "lastMessageUserId": 4400030,
    "markedAsUnread": false,
    "absenceMessageDisabled": null,
    "isFixed": null,
    "isTransfered": false,
    "userId": 4400030,
    "contactId": 11058859,
    "whatsappId": 4400008,
    "whatsappApiId": null,
    "metaId": null,
    "queueId": 4400001,
    "companyId": 38,
    "createdAt": "2026-04-17T09:08:28.000Z",
    "updatedAt": "2026-04-17T16:26:49.000Z",
    "contact": {
      "id": 11058859,
      "name": "Rafael",
      "number": "5513997042664",
      "contactUniqueKey": "5513997042664@38",
      "email": "",
      "profilePicUrl": "",
      "channel": "whatsapp",
      "isGroup": false,
      "userId": null,
      "queueId": 4400001,
      "companyId": 38,
      "lid": "260940805214217@lid",
      "createdAt": "2024-07-11T15:58:30.000Z",
      "updatedAt": "2026-04-17T09:08:25.000Z"
    },
    "user": {
      "photo": "https://d2mytgzbagllkr.cloudfront.net/production/38/logo%20lp.png?Expires=1893456000&Key-Pair-Id=K1I60S7Y6MHGME&Signature=CnErM5h3iIgCHCXsiFsMxxOfXLCBYWn9O08FoGdgoyRoXkffZZKWUcQ0cHxnWMY8OZQOrN5tVwk0370mzYYEZ6jC9hBZwE3IPBv1jPzvCsIwgRiltPE3XUiqapzsaeTPpT4UFkXwaKw~u8~6jGZDVhO0FQL81FOE0kiUlQQFrM-fXsjm1iF5RUjb15LUi2Ax-bYDs06ebAJyVAp-zGvYI4xVtyKzMVNv7J37CRjwjQ~OI0dQgtiaQYM-SBcd6hvwu~K-HtgOJ57wR8CPKOE1YswJ0We1MvNGGwDk5tBsftxACz3-2rNlzUGOCS0TTh94cpROz7tnSEfoE1P04huETw__",
      "id": 4400030,
      "name": "Larissa",
      "email": "representante.laripadilha@gmail.com",
      "passwordHash": "$2a$08$dSq7KFI/WDtcsWOs4uE8c.AC1klbgBZNXFhUmd8qyLFB9bzoIx3r2",
      "tokenVersion": 0,
      "profile": "admin",
      "whatsappId": null,
      "metaId": null,
      "WhatsappApiId": null,
      "ramal": "#null",
      "companyId": 38,
      "active": true,
      "deleted": false,
      "deviceLowMs": 0,
      "isOnline": false,
      "createdAt": "2023-03-24T16:50:22.000Z",
      "updatedAt": "2026-04-17T20:36:59.000Z"
    },
    "whatsapp": {
      "id": 4400008,
      "name": "Mais Granel 🧡",
      "sessionId": 7782,
      "session": "",
      "qrcode": "",
      "status": "CONNECTED",
      "number": "554733075968",
      "battery": null,
      "plugged": null,
      "retries": 0,
      "greetingMessage": null,
      "farewellMessage": null,
      "isDefault": true,
      "allowCall": false,
      "containerIdPort": "d30e6122-07f0-466f-9406-7ea4ef7e4afc:11250",
      "companyId": 38,
      "version": "6.4.11",
      "contactForDisconnectionWarning": "5547997676172",
      "phoneCallMessage": "As chamadas de voz e vídeo estão desabilitadas para esse WhatsApp, por favor enviar uma mensagem de texto ou áudio. Obrigado(a)",
      "createdAt": "2023-01-13T17:15:07.000Z",
      "updatedAt": "2026-04-17T00:07:10.000Z"
    }
  },
  {
    "id": 67148932,
    "ticketUniqueKey": "2148855338@4400008@38",
    "status": "open",
    "inQuestion": false,
    "inTransition": false,
    "origin": "Receptivo",
    "waitTime": "0",
    "attendanceTime": null,
    "closedAt": null,
    "inChatBot": null,
    "chatBotPath": "[4400002]",
    "unreadMessages": 0,
    "lastMessage": "*Larissa*:\nImagina, combinado então ☺️🙏",
    "lastMessageType": "chat",
    "enableAutoFinish": true,
    "autoFinishDate": null,
    "lastMessageDate": "2026-04-17T18:43:52.000Z",
    "lastMessageDateNotFromMe": "2026-04-17T18:41:36.000Z",
    "windowExpirationTimestamp": null,
    "isGroup": false,
    "inAvaliation": null,
    "avaliated": null,
    "avaliationTime": null,
    "messageRetry": null,
    "writingMessage": false,
    "lastMessageUserId": 4400030,
    "markedAsUnread": false,
    "absenceMessageDisabled": null,
    "isFixed": null,
    "isTransfered": false,
    "userId": 4400030,
    "contactId": 2148855338,
    "whatsappId": 4400008,
    "whatsappApiId": null,
    "metaId": null,
    "queueId": 4400001,
    "companyId": 38,
    "createdAt": "2026-04-17T15:28:24.000Z",
    "updatedAt": "2026-04-17T18:43:52.000Z",
    "contact": {
      "id": 2148855338,
      "name": "NUTRIVIA - MARIANA - RS",
      "number": "555191783470",
      "contactUniqueKey": "555191783470@38",
      "email": "",
      "profilePicUrl": "https://d2mytgzbagllkr.cloudfront.net/production/38/38-2148855338-profilePic-1773339461585?Expires=1893456000&Key-Pair-Id=K1I60S7Y6MHGME&Signature=4ccmsRUm2esq7TEiwcjt7e3asj-O2pwCnyYW3UO-96OVtmpC1zlWlNT5qllATH2oGIk4y~rp9JqC4zs35P2Pu2tQC9rwFxBNhgygIHVFPcBv1Kcv6PePs2aDKawhCu4XcNM8sLIVFU0doGWSyzLPnDexXns9mrjvHUksfQGQj9JyeMcFVDIV-PpTBImNU4lgf0T1GdPUCZi2n8JujakjVfg42gwmQi6FNPsypcKeWYhIMd1KuBATwXEsq4DY7K2yHyywzMA6CTXJ4fFOPsu6rm-3WicbWfG6NK9Z6W-eWKWtoplt6zH44iVGv1aJNwBebmcLF3TX8hlin6k3qNwmXA__",
      "channel": "whatsapp",
      "isGroup": false,
      "userId": null,
      "queueId": null,
      "companyId": 38,
      "lid": "183090261528758@lid",
      "createdAt": "2026-02-26T01:35:37.000Z",
      "updatedAt": "2026-03-12T18:18:02.000Z"
    },
    "user": {
      "photo": "https://d2mytgzbagllkr.cloudfront.net/production/38/logo%20lp.png?Expires=1893456000&Key-Pair-Id=K1I60S7Y6MHGME&Signature=CnErM5h3iIgCHCXsiFsMxxOfXLCBYWn9O08FoGdgoyRoXkffZZKWUcQ0cHxnWMY8OZQOrN5tVwk0370mzYYEZ6jC9hBZwE3IPBv1jPzvCsIwgRiltPE3XUiqapzsaeTPpT4UFkXwaKw~u8~6jGZDVhO0FQL81FOE0kiUlQQFrM-fXsjm1iF5RUjb15LUi2Ax-bYDs06ebAJyVAp-zGvYI4xVtyKzMVNv7J37CRjwjQ~OI0dQgtiaQYM-SBcd6hvwu~K-HtgOJ57wR8CPKOE1YswJ0We1MvNGGwDk5tBsftxACz3-2rNlzUGOCS0TTh94cpROz7tnSEfoE1P04huETw__",
      "id": 4400030,
      "name": "Larissa",
      "email": "representante.laripadilha@gmail.com",
      "passwordHash": "$2a$08$dSq7KFI/WDtcsWOs4uE8c.AC1klbgBZNXFhUmd8qyLFB9bzoIx3r2",
      "tokenVersion": 0,
      "profile": "admin",
      "whatsappId": null,
      "metaId": null,
      "WhatsappApiId": null,
      "ramal": "#null",
      "companyId": 38,
      "active": true,
      "deleted": false,
      "deviceLowMs": 0,
      "isOnline": false,
      "createdAt": "2023-03-24T16:50:22.000Z",
      "updatedAt": "2026-04-17T20:36:59.000Z"
    },
    "whatsapp": {
      "id": 4400008,
      "name": "Mais Granel 🧡",
      "sessionId": 7782,
      "session": "",
      "qrcode": "",
      "status": "CONNECTED",
      "number": "554733075968",
      "battery": null,
      "plugged": null,
      "retries": 0,
      "greetingMessage": null,
      "farewellMessage": null,
      "isDefault": true,
      "allowCall": false,
      "containerIdPort": "d30e6122-07f0-466f-9406-7ea4ef7e4afc:11250",
      "companyId": 38,
      "version": "6.4.11",
      "contactForDisconnectionWarning": "5547997676172",
      "phoneCallMessage": "As chamadas de voz e vídeo estão desabilitadas para esse WhatsApp, por favor enviar uma mensagem de texto ou áudio. Obrigado(a)",
      "createdAt": "2023-01-13T17:15:07.000Z",
      "updatedAt": "2026-04-17T00:07:10.000Z"
    }
  },
  {
    "id": 67147812,
    "ticketUniqueKey": "2149026602@64000032@38",
    "status": "open",
    "inQuestion": false,
    "inTransition": false,
    "origin": "Receptivo",
    "waitTime": "0",
    "attendanceTime": null,
    "closedAt": null,
    "inChatBot": null,
    "chatBotPath": "[64001405]",
    "unreadMessages": 0,
    "lastMessage": "*Daiane Stavicki*:\nQuando você analisar e ver certinho me retorna 🙌",
    "lastMessageType": "chat",
    "enableAutoFinish": true,
    "autoFinishDate": null,
    "lastMessageDate": "2026-04-17T18:45:45.000Z",
    "lastMessageDateNotFromMe": "2026-04-17T18:00:18.000Z",
    "windowExpirationTimestamp": null,
    "isGroup": false,
    "inAvaliation": null,
    "avaliated": null,
    "avaliationTime": null,
    "messageRetry": null,
    "writingMessage": false,
    "lastMessageUserId": 4400002,
    "markedAsUnread": false,
    "absenceMessageDisabled": null,
    "isFixed": null,
    "isTransfered": false,
    "userId": 4400002,
    "contactId": 2149026602,
    "whatsappId": 64000032,
    "whatsappApiId": null,
    "metaId": null,
    "queueId": 64000070,
    "companyId": 38,
    "createdAt": "2026-04-17T11:53:57.000Z",
    "updatedAt": "2026-04-17T18:45:45.000Z",
    "contact": {
      "id": 2149026602,
      "name": "Bernardo Blumenau - cozinha industrial e restaurante",
      "number": "554796466099",
      "contactUniqueKey": "554796466099@38",
      "email": "",
      "profilePicUrl": null,
      "channel": "whatsapp",
      "isGroup": false,
      "userId": null,
      "queueId": null,
      "companyId": 38,
      "lid": "240509595455738@lid",
      "createdAt": "2026-04-17T11:53:56.000Z",
      "updatedAt": "2026-04-17T12:00:44.000Z"
    },
    "user": {
      "photo": null,
      "id": 4400002,
      "name": "Daiane Stavicki",
      "email": "daiane@maisgranel.com.br",
      "passwordHash": "$2a$08$lSdHtvPz0XzI/5bUoF5jduuCE2/IR1PeBUtnUZJhofAmyUPHyUg/u",
      "tokenVersion": 0,
      "profile": "admin",
      "whatsappId": 4400008,
      "metaId": null,
      "WhatsappApiId": null,
      "ramal": "#null",
      "companyId": 38,
      "active": true,
      "deleted": false,
      "deviceLowMs": 0,
      "isOnline": false,
      "createdAt": "2022-08-24T12:39:24.000Z",
      "updatedAt": "2026-04-18T10:51:22.000Z"
    },
    "whatsapp": {
      "id": 64000032,
      "name": "Central Vitao 💚",
      "sessionId": null,
      "session": null,
      "qrcode": "",
      "status": "CONNECTED",
      "number": "554135236546",
      "battery": null,
      "plugged": null,
      "retries": 0,
      "greetingMessage": null,
      "farewellMessage": null,
      "isDefault": false,
      "allowCall": false,
      "containerIdPort": "fca4f3ae-6b73-414c-9c44-6c558827e561:whatsapp-microservice",
      "companyId": 38,
      "version": "6.4.11",
      "contactForDisconnectionWarning": "5547997676172",
      "phoneCallMessage": "As chamadas de voz e vídeo estão desabilitadas para esse WhatsApp, por favor enviar uma mensagem de texto ou áudio. Obrigado(a)",
      "createdAt": "2025-04-07T18:06:12.000Z",
      "updatedAt": "2026-04-17T00:04:30.000Z"
    }
  },
  {
    "id": 67148484,
    "ticketUniqueKey": "2149026874@64000032@38",
    "status": "open",
    "inQuestion": false,
    "inTransition": false,
    "origin": "Receptivo",
    "waitTime": "0",
    "attendanceTime": null,
    "closedAt": null,
    "inChatBot": null,
    "chatBotPath": "[64001405]",
    "unreadMessages": 0,
    "lastMessage": "*Larissa*:\nMédia de uma a duas semanas ☺️",
    "lastMessageType": "chat",
    "enableAutoFinish": true,
    "autoFinishDate": null,
    "lastMessageDate": "2026-04-17T19:54:25.000Z",
    "lastMessageDateNotFromMe": "2026-04-17T19:50:38.000Z",
    "windowExpirationTimestamp": null,
    "isGroup": false,
    "inAvaliation": null,
    "avaliated": null,
    "avaliationTime": null,
    "messageRetry": null,
    "writingMessage": false,
    "lastMessageUserId": 4400030,
    "markedAsUnread": false,
    "absenceMessageDisabled": null,
    "isFixed": null,
    "isTransfered": false,
    "userId": 4400030,
    "contactId": 2149026874,
    "whatsappId": 64000032,
    "whatsappApiId": null,
    "metaId": null,
    "queueId": 64000070,
    "companyId": 38,
    "createdAt": "2026-04-17T14:01:28.000Z",
    "updatedAt": "2026-04-17T19:54:25.000Z",
    "contact": {
      "id": 2149026874,
      "name": "ALCIDÉSIA - PE",
      "number": "558197718468",
      "contactUniqueKey": "558197718468@38",
      "email": "",
      "profilePicUrl": "https://d2mytgzbagllkr.cloudfront.net/production/38/38-2149026874-profilePic-1776449041377?Expires=1893456000&Key-Pair-Id=K1I60S7Y6MHGME&Signature=PhZHJ~UJ9Tdn5UTUJOFDBjGMX9YcxIonX2fx15nQ5yHENgfLuvekfbyYlRpqpvkhnZOVq-elHtIQUeg-sP~3u21Aoqa8nVE7k1leQix4M1-~~Ciy3x0f9VYDQb16msWfDYDU9jvH~V61VGmqCpTNa1ejHciI05-S4nFob1ie8clb3o82dh5OFCwcMmMGC14DEsr4OUyJ7FZ~maYuherdhV31Ev36HN8wQVlaFKxvL0rYDQpXCTzAHxS5Tel~wMdi4C4~5K-x7eJzGimC1qK-KxxHUpqUysDGTXwOhPR5nnNbVvXUPlgalQySbdP9uBG2TKXxdfcAIE7OTIIPOGsieA__",
      "channel": "whatsapp",
      "isGroup": false,
      "userId": null,
      "queueId": null,
      "companyId": 38,
      "lid": "173615614013472@lid",
      "createdAt": "2026-04-17T14:01:28.000Z",
      "updatedAt": "2026-04-17T18:04:01.000Z"
    },
    "user": {
      "photo": "https://d2mytgzbagllkr.cloudfront.net/production/38/logo%20lp.png?Expires=1893456000&Key-Pair-Id=K1I60S7Y6MHGME&Signature=CnErM5h3iIgCHCXsiFsMxxOfXLCBYWn9O08FoGdgoyRoXkffZZKWUcQ0cHxnWMY8OZQOrN5tVwk0370mzYYEZ6jC9hBZwE3IPBv1jPzvCsIwgRiltPE3XUiqapzsaeTPpT4UFkXwaKw~u8~6jGZDVhO0FQL81FOE0kiUlQQFrM-fXsjm1iF5RUjb15LUi2Ax-bYDs06ebAJyVAp-zGvYI4xVtyKzMVNv7J37CRjwjQ~OI0dQgtiaQYM-SBcd6hvwu~K-HtgOJ57wR8CPKOE1YswJ0We1MvNGGwDk5tBsftxACz3-2rNlzUGOCS0TTh94cpROz7tnSEfoE1P04huETw__",
      "id": 4400030,
      "name": "Larissa",
      "email": "representante.laripadilha@gmail.com",
      "passwordHash": "$2a$08$dSq7KFI/WDtcsWOs4uE8c.AC1klbgBZNXFhUmd8qyLFB9bzoIx3r2",
      "tokenVersion": 0,
      "profile": "admin",
      "whatsappId": null,
      "metaId": null,
      "WhatsappApiId": null,
      "ramal": "#null",
      "companyId": 38,
      "active": true,
      "deleted": false,
      "deviceLowMs": 0,
      "isOnline": false,
      "createdAt": "2023-03-24T16:50:22.000Z",
      "updatedAt": "2026-04-17T20:36:59.000Z"
    },
    "whatsapp": {
      "id": 64000032,
      "name": "Central Vitao 💚",
      "sessionId": null,
      "session": null,
      "qrcode": "",
      "status": "CONNECTED",
      "number": "554135236546",
      "battery": null,
      "plugged": null,
      "retries": 0,
      "greetingMessage": null,
      "farewellMessage": null,
      "isDefault": false,
      "allowCall": false,
      "containerIdPort": "fca4f3ae-6b73-414c-9c44-6c558827e561:whatsapp-microservice",
      "companyId": 38,
      "version": "6.4.11",
      "contactForDisconnectionWarning": "5547997676172",
      "phoneCallMessage": "As chamadas de voz e vídeo estão desabilitadas para esse WhatsApp, por favor enviar uma mensagem de texto ou áudio. Obrigado(a)",
      "createdAt": "2025-04-07T18:06:12.000Z",
      "updatedAt": "2026-04-17T00:04:30.000Z"
    }
  },
  {
    "id": 67150140,
    "ticketUniqueKey": "2148612542@64000032@38",
    "status": "open",
    "inQuestion": null,
    "inTransition": null,
    "origin": "Ativo",
    "waitTime": null,
    "attendanceTime": null,
    "closedAt": null,
    "inChatBot": null,
    "chatBotPath": null,
    "unreadMessages": 0,
    "lastMessage": "*Larissa*:\nOpaaa, que maravilha querida!!",
    "lastMessageType": "chat",
    "enableAutoFinish": true,
    "autoFinishDate": null,
    "lastMessageDate": "2026-04-17T19:55:21.000Z",
    "lastMessageDateNotFromMe": "2026-04-17T19:54:07.000Z",
    "windowExpirationTimestamp": null,
    "isGroup": false,
    "inAvaliation": null,
    "avaliated": null,
    "avaliationTime": null,
    "messageRetry": null,
    "writingMessage": null,
    "lastMessageUserId": 4400030,
    "markedAsUnread": false,
    "absenceMessageDisabled": null,
    "isFixed": null,
    "isTransfered": null,
    "userId": 4400030,
    "contactId": 2148612542,
    "whatsappId": 64000032,
    "whatsappApiId": null,
    "metaId": null,
    "queueId": 64000070,
    "companyId": 38,
    "createdAt": "2026-04-17T19:27:48.000Z",
    "updatedAt": "2026-04-17T19:55:21.000Z",
    "contact": {
      "id": 2148612542,
      "name": "GRAO D'TERRA - TAMIRES - ES",
      "number": "5528999268380",
      "contactUniqueKey": "5528999268380@38",
      "email": "",
      "profilePicUrl": "https://d2mytgzbagllkr.cloudfront.net/production/38/38-2148612542-profilePic-1776454103409?Expires=1893456000&Key-Pair-Id=K1I60S7Y6MHGME&Signature=TgAHyyxmTAryuUUMghuiWN6EYMb-3bh0WoDIxgJ87Rw7nAj~vcKcWs4F-gQF-3w3GtCZt3W-NY8Z-r9q8qclR-JIotJvZkvlS5QjuK4kq9LoR82RlVpaVjchCFqzQnEPhcKvHrsaFTbzqqz2gTWAUFTlNryygepG22Bw8pBDrAyRrHrvSKB2Kjn9Gk1mH5c5UiaVqsFatJceHwmrDvLEfrFiaRVVslN3cF5npbdDX2667LLcaxN4KQwzM0qlm5MkUs2uvdKRDUevtM8Aw-qXly3RXpge6RKsM4U~G7bu~isepwYOjJhCE78JpJ7zzemoIfwoT4z--~ONkPLHNrXGuw__",
      "channel": "whatsapp",
      "isGroup": false,
      "userId": null,
      "queueId": null,
      "companyId": 38,
      "lid": "190284314972240@lid",
      "createdAt": "2025-12-08T18:34:03.000Z",
      "updatedAt": "2026-04-17T19:28:23.000Z"
    },
    "user": {
      "photo": "https://d2mytgzbagllkr.cloudfront.net/production/38/logo%20lp.png?Expires=1893456000&Key-Pair-Id=K1I60S7Y6MHGME&Signature=CnErM5h3iIgCHCXsiFsMxxOfXLCBYWn9O08FoGdgoyRoXkffZZKWUcQ0cHxnWMY8OZQOrN5tVwk0370mzYYEZ6jC9hBZwE3IPBv1jPzvCsIwgRiltPE3XUiqapzsaeTPpT4UFkXwaKw~u8~6jGZDVhO0FQL81FOE0kiUlQQFrM-fXsjm1iF5RUjb15LUi2Ax-bYDs06ebAJyVAp-zGvYI4xVtyKzMVNv7J37CRjwjQ~OI0dQgtiaQYM-SBcd6hvwu~K-HtgOJ57wR8CPKOE1YswJ0We1MvNGGwDk5tBsftxACz3-2rNlzUGOCS0TTh94cpROz7tnSEfoE1P04huETw__",
      "id": 4400030,
      "name": "Larissa",
      "email": "representante.laripadilha@gmail.com",
      "passwordHash": "$2a$08$dSq7KFI/WDtcsWOs4uE8c.AC1klbgBZNXFhUmd8qyLFB9bzoIx3r2",
      "tokenVersion": 0,
      "profile": "admin",
      "whatsappId": null,
      "metaId": null,
      "WhatsappApiId": null,
      "ramal": "#null",
      "companyId": 38,
      "active": true,
      "deleted": false,
      "deviceLowMs": 0,
      "isOnline": false,
      "createdAt": "2023-03-24T16:50:22.000Z",
      "updatedAt": "2026-04-17T20:36:59.000Z"
    },
    "whatsapp": {
      "id": 64000032,
      "name": "Central Vitao 💚",
      "sessionId": null,
      "session": null,
      "qrcode": "",
      "status": "CONNECTED",
      "number": "554135236546",
      "battery": null,
      "plugged": null,
      "retries": 0,
      "greetingMessage": null,
      "farewellMessage": null,
      "isDefault": false,
      "allowCall": false,
      "containerIdPort": "fca4f3ae-6b73-414c-9c44-6c558827e561:whatsapp-microservice",
      "companyId": 38,
      "version": "6.4.11",
      "contactForDisconnectionWarning": "5547997676172",
      "phoneCallMessage": "As chamadas de voz e vídeo estão desabilitadas para esse WhatsApp, por favor enviar uma mensagem de texto ou áudio. Obrigado(a)",
      "createdAt": "2025-04-07T18:06:12.000Z",
      "updatedAt": "2026-04-17T00:04:30.000Z"
    }
  },
  {
    "id": 67151014,
    "ticketUniqueKey": "2149027920@64000032@38",
    "status": "pending",
    "inQuestion": false,
    "inTransition": false,
    "origin": "Receptivo",
    "waitTime": "0",
    "attendanceTime": null,
    "closedAt": null,
    "inChatBot": null,
    "chatBotPath": "[64001405]",
    "unreadMessages": 1,
    "lastMessage": "Boa Noite gostaria de receber catálogo e tabela de preços por favor",
    "lastMessageType": "chat",
    "enableAutoFinish": true,
    "autoFinishDate": null,
    "lastMessageDate": "2026-04-17T23:14:59.000Z",
    "lastMessageDateNotFromMe": "2026-04-17T23:14:59.000Z",
    "windowExpirationTimestamp": null,
    "isGroup": false,
    "inAvaliation": null,
    "avaliated": null,
    "avaliationTime": null,
    "messageRetry": null,
    "writingMessage": false,
    "lastMessageUserId": null,
    "markedAsUnread": false,
    "absenceMessageDisabled": null,
    "isFixed": null,
    "isTransfered": null,
    "userId": null,
    "contactId": 2149027920,
    "whatsappId": 64000032,
    "whatsappApiId": null,
    "metaId": null,
    "queueId": 64000070,
    "companyId": 38,
    "createdAt": "2026-04-17T23:14:59.000Z",
    "updatedAt": "2026-04-17T23:15:01.000Z",
    "contact": {
      "id": 2149027920,
      "name": "Edmilson",
      "number": "553599627133",
      "contactUniqueKey": "553599627133@38",
      "email": "",
      "profilePicUrl": null,
      "channel": "whatsapp",
      "isGroup": false,
      "userId": null,
      "queueId": null,
      "companyId": 38,
      "lid": "276256759250986@lid",
      "createdAt": "2026-04-17T23:14:59.000Z",
      "updatedAt": "2026-04-17T23:14:59.000Z"
    },
    "user": null,
    "whatsapp": {
      "id": 64000032,
      "name": "Central Vitao 💚",
      "sessionId": null,
      "session": null,
      "qrcode": "",
      "status": "CONNECTED",
      "number": "554135236546",
      "battery": null,
      "plugged": null,
      "retries": 0,
      "greetingMessage": null,
      "farewellMessage": null,
      "isDefault": false,
      "allowCall": false,
      "containerIdPort": "fca4f3ae-6b73-414c-9c44-6c558827e561:whatsapp-microservice",
      "companyId": 38,
      "version": "6.4.11",
      "contactForDisconnectionWarning": "5547997676172",
      "phoneCallMessage": "As chamadas de voz e vídeo estão desabilitadas para esse WhatsApp, por favor enviar uma mensagem de texto ou áudio. Obrigado(a)",
      "createdAt": "2025-04-07T18:06:12.000Z",
      "updatedAt": "2026-04-17T00:04:30.000Z"
    }
  },
  {
    "id": 67151178,
    "ticketUniqueKey": "2149028053@64000032@38",
    "status": "pending",
    "inQuestion": false,
    "inTransition": false,
    "origin": "Receptivo",
    "waitTime": "1",
    "attendanceTime": null,
    "closedAt": null,
    "inChatBot": null,
    "chatBotPath": "[64001405]",
    "unreadMessages": 2,
    "lastMessage": "👋 Seja muito bem-vindo ao nosso canal de atendimento para lojistas!\nÉ um prazer receber você aqui.\n\nNo momento nossos atendentes não estão disponíveis. Nosso horário de atendimento é de 08h às 18h. Mas fique tranquilo(a) que assim que retornarmos você será respondido(a).",
    "lastMessageType": "chat",
    "enableAutoFinish": true,
    "autoFinishDate": null,
    "lastMessageDate": "2026-04-18T03:03:13.000Z",
    "lastMessageDateNotFromMe": "2026-04-18T03:03:12.000Z",
    "windowExpirationTimestamp": null,
    "isGroup": false,
    "inAvaliation": null,
    "avaliated": null,
    "avaliationTime": null,
    "messageRetry": 1,
    "writingMessage": false,
    "lastMessageUserId": null,
    "markedAsUnread": false,
    "absenceMessageDisabled": null,
    "isFixed": null,
    "isTransfered": null,
    "userId": null,
    "contactId": 2149028053,
    "whatsappId": 64000032,
    "whatsappApiId": null,
    "metaId": null,
    "queueId": 64000070,
    "companyId": 38,
    "createdAt": "2026-04-18T03:03:04.000Z",
    "updatedAt": "2026-04-18T03:03:13.000Z",
    "contact": {
      "id": 2149028053,
      "name": "Alex",
      "number": "5521982916621",
      "contactUniqueKey": "5521982916621@38",
      "email": "",
      "profilePicUrl": null,
      "channel": "whatsapp",
      "isGroup": false,
      "userId": null,
      "queueId": null,
      "companyId": 38,
      "lid": "120452458488045@lid",
      "createdAt": "2026-04-18T03:03:04.000Z",
      "updatedAt": "2026-04-18T03:03:04.000Z"
    },
    "user": null,
    "whatsapp": {
      "id": 64000032,
      "name": "Central Vitao 💚",
      "sessionId": null,
      "session": null,
      "qrcode": "",
      "status": "CONNECTED",
      "number": "554135236546",
      "battery": null,
      "plugged": null,
      "retries": 0,
      "greetingMessage": null,
      "farewellMessage": null,
      "isDefault": false,
      "allowCall": false,
      "containerIdPort": "fca4f3ae-6b73-414c-9c44-6c558827e561:whatsapp-microservice",
      "companyId": 38,
      "version": "6.4.11",
      "contactForDisconnectionWarning": "5547997676172",
      "phoneCallMessage": "As chamadas de voz e vídeo estão desabilitadas para esse WhatsApp, por favor enviar uma mensagem de texto ou áudio. Obrigado(a)",
      "createdAt": "2025-04-07T18:06:12.000Z",
      "updatedAt": "2026-04-17T00:04:30.000Z"
    }
  },
  {
    "id": 67151554,
    "ticketUniqueKey": "2149028246@4400008@38",
    "status": "pending",
    "inQuestion": false,
    "inTransition": false,
    "origin": "Receptivo",
    "waitTime": "0",
    "attendanceTime": null,
    "closedAt": null,
    "inChatBot": null,
    "chatBotPath": "[4400002]",
    "unreadMessages": 1,
    "lastMessage": "Oi",
    "lastMessageType": "chat",
    "enableAutoFinish": true,
    "autoFinishDate": null,
    "lastMessageDate": "2026-04-18T13:00:57.000Z",
    "lastMessageDateNotFromMe": "2026-04-18T13:00:57.000Z",
    "windowExpirationTimestamp": null,
    "isGroup": false,
    "inAvaliation": null,
    "avaliated": null,
    "avaliationTime": null,
    "messageRetry": null,
    "writingMessage": false,
    "lastMessageUserId": null,
    "markedAsUnread": false,
    "absenceMessageDisabled": null,
    "isFixed": null,
    "isTransfered": null,
    "userId": null,
    "contactId": 2149028246,
    "whatsappId": 4400008,
    "whatsappApiId": null,
    "metaId": null,
    "queueId": 4400001,
    "companyId": 38,
    "createdAt": "2026-04-18T13:00:56.000Z",
    "updatedAt": "2026-04-18T13:00:58.000Z",
    "contact": {
      "id": 2149028246,
      "name": "Cajuzinho Castanhas",
      "number": "553497162408",
      "contactUniqueKey": "553497162408@38",
      "email": "",
      "profilePicUrl": null,
      "channel": "whatsapp",
      "isGroup": false,
      "userId": null,
      "queueId": null,
      "companyId": 38,
      "lid": "227071129337897@lid",
      "createdAt": "2026-04-18T13:00:56.000Z",
      "updatedAt": "2026-04-18T13:00:56.000Z"
    },
    "user": null,
    "whatsapp": {
      "id": 4400008,
      "name": "Mais Granel 🧡",
      "sessionId": 7782,
      "session": "",
      "qrcode": "",
      "status": "CONNECTED",
      "number": "554733075968",
      "battery": null,
      "plugged": null,
      "retries": 0,
      "greetingMessage": null,
      "farewellMessage": null,
      "isDefault": true,
      "allowCall": false,
      "containerIdPort": "d30e6122-07f0-466f-9406-7ea4ef7e4afc:11250",
      "companyId": 38,
      "version": "6.4.11",
      "contactForDisconnectionWarning": "5547997676172",
      "phoneCallMessage": "As chamadas de voz e vídeo estão desabilitadas para esse WhatsApp, por favor enviar uma mensagem de texto ou áudio. Obrigado(a)",
      "createdAt": "2023-01-13T17:15:07.000Z",
      "updatedAt": "2026-04-17T00:07:10.000Z"
    }
  },
  {
    "id": 67151807,
    "ticketUniqueKey": "2149028363@4400008@38",
    "status": "pending",
    "inQuestion": false,
    "inTransition": false,
    "origin": "Receptivo",
    "waitTime": "0",
    "attendanceTime": null,
    "closedAt": null,
    "inChatBot": null,
    "chatBotPath": "[4400002]",
    "unreadMessages": 2,
    "lastMessage": "Pode me passar tabela de produtos por favor?",
    "lastMessageType": "chat",
    "enableAutoFinish": true,
    "autoFinishDate": null,
    "lastMessageDate": "2026-04-18T14:30:53.000Z",
    "lastMessageDateNotFromMe": "2026-04-18T14:30:53.000Z",
    "windowExpirationTimestamp": null,
    "isGroup": false,
    "inAvaliation": null,
    "avaliated": null,
    "avaliationTime": null,
    "messageRetry": null,
    "writingMessage": false,
    "lastMessageUserId": null,
    "markedAsUnread": false,
    "absenceMessageDisabled": null,
    "isFixed": null,
    "isTransfered": null,
    "userId": null,
    "contactId": 2149028363,
    "whatsappId": 4400008,
    "whatsappApiId": null,
    "metaId": null,
    "queueId": 4400001,
    "companyId": 38,
    "createdAt": "2026-04-18T14:30:28.000Z",
    "updatedAt": "2026-04-18T14:30:54.000Z",
    "contact": {
      "id": 2149028363,
      "name": "Nayara",
      "number": "553298211649",
      "contactUniqueKey": "553298211649@38",
      "email": "",
      "profilePicUrl": null,
      "channel": "whatsapp",
      "isGroup": false,
      "userId": null,
      "queueId": null,
      "companyId": 38,
      "lid": "122969342898373@lid",
      "createdAt": "2026-04-18T14:30:28.000Z",
      "updatedAt": "2026-04-18T14:30:28.000Z"
    },
    "user": null,
    "whatsapp": {
      "id": 4400008,
      "name": "Mais Granel 🧡",
      "sessionId": 7782,
      "session": "",
      "qrcode": "",
      "status": "CONNECTED",
      "number": "554733075968",
      "battery": null,
      "plugged": null,
      "retries": 0,
      "greetingMessage": null,
      "farewellMessage": null,
      "isDefault": true,
      "allowCall": false,
      "containerIdPort": "d30e6122-07f0-466f-9406-7ea4ef7e4afc:11250",
      "companyId": 38,
      "version": "6.4.11",
      "contactForDisconnectionWarning": "5547997676172",
      "phoneCallMessage": "As chamadas de voz e vídeo estão desabilitadas para esse WhatsApp, por favor enviar uma mensagem de texto ou áudio. Obrigado(a)",
      "createdAt": "2023-01-13T17:15:07.000Z",
      "updatedAt": "2026-04-17T00:07:10.000Z"
    }
  }
]